util/__init__.py
util/constants.py
util/datetime.py
util/logging.py
util/multi_dict.py
util/options.py
util/pattern.py
util/plot.py
util/str.py
util/batch/__init__.py
util/batch/general/__init__.py
util/batch/general/system.py
util/batch/nec/__init__.py
util/batch/nec/constants.py
util/batch/nec/system.py
util/batch/rz/__init__.py
util/batch/rz/constants.py
util/batch/rz/system.py
util/batch/universal/__init__.py
util/batch/universal/system.py
util/cache/__init__.py
util/cache/auxiliary.py
util/cache/file.py
util/cache/memory.py
util/index_database/__init__.py
util/index_database/array_and_txt_file_based.py
util/index_database/array_based.py
util/index_database/fs_based.py
util/index_database/general.py
util/index_database/petsc_file_based.py
util/index_database/txt_file_based.py
util/io/__init__.py
util/io/env.py
util/io/fs.py
util/io/hdf5.py
util/io/io.py
util/io/matlab.py
util/io/netcdf.py
util/io/np.py
util/io/object.py
util/io/universal.py
util/io/filelock/__init__.py
util/io/filelock/general.py
util/io/filelock/np.py
util/io/filelock/unix.py
util/io/filelock/unix_exclusive.py
util/io/matrix/__init__.py
util/io/matrix/market.py
util/io/matrix/sparse.py
util/math/__init__.py
util/math/check.py
util/math/finite_differences.py
util/math/interpolate.py
util/math/matrix.py
util/math/sort.py
util/math/spherical.py
util/math/util.py
util/math/optimize/__init__.py
util/math/optimize/universal.py
util/math/optimize/with_deap.py
util/math/optimize/with_scipy.py
util/math/sparse/__init__.py
util/math/sparse/check.py
util/math/sparse/create.py
util/math/sparse/linalg.py
util/math/sparse/solve.py
util/math/sparse/decompose/__init__.py
util/math/sparse/decompose/constants.py
util/math/sparse/decompose/run_cholesky.py
util/math/sparse/decompose/run_positive_definit_approximation.py
util/math/sparse/decompose/with_cholmod.py
util/math/sparse/decompose/with_python.py
util/observable/__init__.py
utillib-0.2.dist-info/DESCRIPTION.rst
utillib-0.2.dist-info/METADATA
utillib-0.2.dist-info/RECORD
utillib-0.2.dist-info/WHEEL
utillib-0.2.dist-info/metadata.json
utillib-0.2.dist-info/top_level.txt
