Metadata-Version: 2.0
Name: utillib
Version: 0.2
Summary: util functions
Home-page: https://github.com/jor-/util
Author: Joscha Reimer
Author-email: jor@informatik.uni-kiel.de
License: GPLv3+
Keywords: utility auxiliary functions
Platform: UNKNOWN
Classifier: Development Status :: 3 - Alpha
Classifier: Intended Audience :: Developers
Classifier: Intended Audience :: Science/Research
Classifier: Topic :: Software Development :: Libraries :: Python Modules
Classifier: License :: OSI Approved :: GNU General Public License v3 or later (GPLv3+)
Classifier: Programming Language :: Python :: 3
Requires-Dist: numpy
Provides-Extra: cache
Requires-Dist: cachetools; extra == 'cache'
Provides-Extra: cholmod
Requires-Dist: scikit-sparse (>=0.4.1); extra == 'cholmod'
Requires-Dist: scipy (>=0.19); extra == 'cholmod'
Provides-Extra: colored_log
Requires-Dist: colorlog; extra == 'colored_log'
Provides-Extra: deap
Requires-Dist: deap; extra == 'deap'
Provides-Extra: hdf5
Requires-Dist: h5py; extra == 'hdf5'
Provides-Extra: interpolate
Requires-Dist: scipy (>=0.17); extra == 'interpolate'
Provides-Extra: market
Requires-Dist: scipy; extra == 'market'
Provides-Extra: matlab
Requires-Dist: scipy; extra == 'matlab'
Provides-Extra: multi_dict_stats
Requires-Dist: scipy; extra == 'multi_dict_stats'
Provides-Extra: netcdf
Requires-Dist: netCDF4; extra == 'netcdf'
Requires-Dist: scipy; extra == 'netcdf'
Provides-Extra: optimize
Requires-Dist: scipy; extra == 'optimize'
Provides-Extra: options
Requires-Dist: h5py; extra == 'options'
Provides-Extra: petsc
Requires-Dist: petsc4py; extra == 'petsc'
Provides-Extra: plot
Requires-Dist: matplotlib; extra == 'plot'
Provides-Extra: scoop
Requires-Dist: scoop; extra == 'scoop'
Provides-Extra: sorted_multi_dict
Requires-Dist: blist; extra == 'sorted_multi_dict'
Provides-Extra: sparse
Requires-Dist: scipy (>=0.19); extra == 'sparse'
